[
  {
    "Name": "Change Region to China",
    "URL": "https://github.com/straight-tamago-sub/vdfStore/raw/main/Change_region_to_China.vdf",
    "Comment": "地域を中国に設定します。",
    "Submitter": "yyyywaiwai",
    "SubmitDate": "2022.02.20",
    "Badge": "",
    "Link": "Link",
    "ID": "ID"
  },
  {
    "Name": "Customize Settings App",
    "URL": "https://github.com/straight-tamago-sub/vdfStore/raw/main/Settings.plist.vdf",
    "Comment": "設定画面をカスタマイズします。",
    "Submitter": "straight-tamago",
    "SubmitDate": "2022.02.20",
    "Badge": "",
    "Link": "Link",
    "ID": "ID"
  }
]
